mybar/__init__.py
mybar/__main__.py
mybar/_setups.py
mybar/_types.py
mybar/bar.py
mybar/cli.py
mybar/constants.py
mybar/custom_types.py
mybar/errors.py
mybar/field.py
mybar/field_funcs.py
mybar/formatting.py
mybar/log.py
mybar/namespaces.py
mybar/utils.py
mybar-0.14.1.dist-info/LICENSE
mybar-0.14.1.dist-info/METADATA
mybar-0.14.1.dist-info/WHEEL
mybar-0.14.1.dist-info/top_level.txt
mybar-0.14.1.dist-info/RECORD
