Metadata-Version: 2.1
Name: mybar
Version: 0.14.1
Summary: Craft highly customizable status bars with ease.
Home-page: https://github.com/akyuute/mybar
Author: akyuute
License: MIT
Project-URL: GitHub: repo, https://github.com/akyuute/mybar
Project-URL: ReadTheDocs: documentation, https://mybar.readthedocs.io
Keywords: status bar,bar,command line,i3,threads,async,API
Platform: Platform Independent
Classifier: Development Status :: 3 - Alpha
Classifier: Environment :: Console
Classifier: Framework :: AsyncIO
Classifier: Intended Audience :: End Users/Desktop
Classifier: License :: OSI Approved :: MIT License
Classifier: Natural Language :: English
Classifier: Operating System :: OS Independent
Classifier: Programming Language :: Python :: 3
Classifier: Programming Language :: Python :: 3.12
Classifier: Topic :: Desktop Environment
Classifier: Topic :: Utilities
Requires-Python: >=3.12
License-File: LICENSE
Requires-Dist: psutil
Requires-Dist: scuff
